LICENSE
MANIFEST.in
README.md
setup.cfg
setup.py
versioneer.py
kernda/__init__.py
kernda/_version.py
kernda/cli.py
kernda.egg-info/PKG-INFO
kernda.egg-info/SOURCES.txt
kernda.egg-info/dependency_links.txt
kernda.egg-info/entry_points.txt
kernda.egg-info/top_level.txt
test/test_cli.py