Metadata-Version: 1.0
Name: kernda
Version: 0.2.1
Summary: Add conda environment activation to an IPython kernel spec
Home-page: https://github.com/parente/kernda
Author: MaxPoint Interactive
Author-email: peter.parente@maxpoint.com
License: BSD 3-Clause
Platform: Linux
Platform: Mac OSX
